rawdog_django_orm/__init__.py
rawdog_django_orm-0.0.5.dist-info/METADATA
rawdog_django_orm-0.0.5.dist-info/WHEEL
rawdog_django_orm-0.0.5.dist-info/top_level.txt
rawdog_django_orm-0.0.5.dist-info/RECORD
