Metadata-Version: 2.2
Name: rawdog_django_orm
Version: 0.0.5
Summary: Utilities for using the django orm outside of django
Home-page: https://github.com/orgs/trysimpler/rawdog_django_orm
Author: George3d6
Classifier: Programming Language :: Python :: 3
Classifier: License :: OSI Approved :: MIT License
Requires-Dist: django
Requires-Dist: starlette
Dynamic: author
Dynamic: classifier
Dynamic: description
Dynamic: description-content-type
Dynamic: home-page
Dynamic: requires-dist
Dynamic: summary
